django_thumb-1.0.1.dist-info/METADATA
django_thumb-1.0.1.dist-info/RECORD
django_thumb-1.0.1.dist-info/WHEEL
django_thumb-1.0.1.dist-info/top_level.txt
thumb/__init__.py
thumb/admin.py
thumb/apps.py
thumb/models.py
thumb/tests.py
thumb/views.py
thumb/fields/__init__.py
thumb/fields/django_thumbnail.py
thumb/fields/cascade_data/__init__.py
thumb/fields/cascade_data/data.py
thumb/fields/cascade_data/xml_cascades/haarcascade_frontalface_default.xml
thumb/fields/cascade_data/xml_cascades/haarcascade_smile.xml
thumb/fields/colored_text_field/__init__.py
thumb/fields/colored_text_field/form_field.py
thumb/fields/colored_text_field/widget.py
thumb/fields/colorfield/__init__.py
thumb/fields/colorfield/widget.py
thumb/fields/image_thumnail_field/__init__.py
thumb/fields/image_thumnail_field/form_field.py
thumb/fields/image_thumnail_field/model_field.py
thumb/fields/image_thumnail_field/widget.py
thumb/fields/video_thumbnail_field/__init__.py
thumb/fields/video_thumbnail_field/form_field.py
thumb/fields/video_thumbnail_field/model_field.py
thumb/fields/video_thumbnail_field/widget.py
thumb/migrations/__init__.py
thumb/static/colorfield/add_jscolor.js
thumb/static/colorfield/colorfield.min.js
thumb/static/thumbnail-field/thumbnail-field.css
thumb/static/thumbnail-field/thumbnail-field.min.css
thumb/templates/coloredtext_field.html
thumb/templates/colorfield.html
thumb/templates/image_thumbnail.html
thumb/templates/thumbnail_base.html
thumb/templates/video_thumbnail.html
