Metadata-Version: 2.1
Name: django-thumb
Version: 1.0.1
Summary: A simple Django model fields to generate images from videos or write on images
Home-page: https://github.com/AmrAnwar/django-thumb
Author: AmrAnwar
Author-email: amranwar945@gmail.com
License: BSD License
Platform: UNKNOWN
Classifier: Environment :: Web Environment
Classifier: Framework :: Django
Classifier: Intended Audience :: Developers
Classifier: License :: OSI Approved :: BSD License
Classifier: Operating System :: OS Independent
Classifier: Programming Language :: Python :: 3
Classifier: Programming Language :: Python :: 3.4
Classifier: Programming Language :: Python :: 3.5
Classifier: Programming Language :: Python :: 3.6
Classifier: Topic :: Internet :: WWW/HTTP
Classifier: Topic :: Internet :: WWW/HTTP :: Dynamic Content
Requires-Dist: Django (>=2.0.0)
Requires-Dist: numpy (>=1.14)
Requires-Dist: opencv-python (>=3.4.0.12)
Requires-Dist: Pillow (>=5.1.0)
